tidy3d/__init__.py
tidy3d/constants.py
tidy3d/dispersion.py
tidy3d/grid.py
tidy3d/json_ops.py
tidy3d/material.py
tidy3d/material_library.py
tidy3d/simulation.py
tidy3d/structure.py
tidy3d/mode/Mode.py
tidy3d/mode/ModePlane.py
tidy3d/mode/__init__.py
tidy3d/mode/derivatives.py
tidy3d/mode/dot_product.py
tidy3d/mode/solver.py
tidy3d/monitor/Monitor.py
tidy3d/monitor/MonitorData.py
tidy3d/monitor/__init__.py
tidy3d/monitor/_simulation.py
tidy3d/near2far/Near2Far.py
tidy3d/near2far/__init__.py
tidy3d/source/Source.py
tidy3d/source/SourceData.py
tidy3d/source/SourceTime.py
tidy3d/source/__init__.py
tidy3d/source/_simulation.py
tidy3d/utils/__init__.py
tidy3d/utils/check.py
tidy3d/utils/em.py
tidy3d/utils/geom.py
tidy3d/utils/log.py
tidy3d/utils/misc.py
tidy3d/viz/__init__.py
tidy3d/viz/field.py
tidy3d/viz/mode.py
tidy3d/viz/source.py
tidy3d/viz/structure.py
tidy3d/web/__init__.py
tidy3d/web/authentication.py
tidy3d/web/config.py
tidy3d/web/httputils.py
tidy3d/web/s3utils.py
tidy3d/web/webapi.py
tidy3d_dev-21.2.1.10.dist-info/LICENSE
tidy3d_dev-21.2.1.10.dist-info/METADATA
tidy3d_dev-21.2.1.10.dist-info/WHEEL
tidy3d_dev-21.2.1.10.dist-info/dependency_links.txt
tidy3d_dev-21.2.1.10.dist-info/top_level.txt
tidy3d_dev-21.2.1.10.dist-info/RECORD
